ncaa_march_madness_2020/__init__.py
ncaa_march_madness_2020/_nbdev.py
ncaa_march_madness_2020/baseline.py
ncaa_march_madness_2020-0.0.2.dist-info/METADATA
ncaa_march_madness_2020-0.0.2.dist-info/WHEEL
ncaa_march_madness_2020-0.0.2.dist-info/entry_points.txt
ncaa_march_madness_2020-0.0.2.dist-info/top_level.txt
ncaa_march_madness_2020-0.0.2.dist-info/RECORD
