Metadata-Version: 2.1
Name: ncaa-march-madness-2020
Version: 0.0.2
Summary: Internal functions for NCAA March Madness 2020
Home-page: https://github.com/JiaxiangBU/ncaa_march_madness_2020
Author: Jiaxiang Li and Jiatao Li and Zhipeng Liang and Yue Pan
Author-email: alex.lijiaxiang@foxmail.com
License: Apache Software License 2.0
Keywords: kaggle
Platform: UNKNOWN
Classifier: Development Status :: 3 - Alpha
Classifier: Intended Audience :: Developers
Classifier: License :: OSI Approved :: Apache Software License
Classifier: Natural Language :: English
Classifier: Programming Language :: Python :: 3.6
Classifier: Programming Language :: Python :: 3.7
Classifier: Programming Language :: Python :: 3.8
Requires-Python: >=3.6
